sorrek_salesforce/__init__.py
sorrek_salesforce/__version__.py
sorrek_salesforce/app.py
sorrek_salesforce-1.0.3.dist-info/LICENSE
sorrek_salesforce-1.0.3.dist-info/METADATA
sorrek_salesforce-1.0.3.dist-info/WHEEL
sorrek_salesforce-1.0.3.dist-info/top_level.txt
sorrek_salesforce-1.0.3.dist-info/RECORD
