Metadata-Version: 2.1
Name: sorrek-salesforce
Version: 1.0.3
Summary: Functions to read, update, and backup Salesforce.
Author-email: Ariel Lavi <ariel@sorrek.io>
Project-URL: Homepage, https://github.com/sorrek/sorrek-salesforce
Project-URL: Bug Tracker, https://github.com/sorrek/sorrek-salesforce/issues
Classifier: Programming Language :: Python :: 3
Classifier: License :: OSI Approved :: MIT License
Classifier: Operating System :: OS Independent
Requires-Python: >=3.7
License-File: LICENSE
